{
	"dirt": {
		"health": 100,
		"collision": true,
		"diggable": true,
		"sprite": "dirt.png",
		"drops": "dirt",
		"dropAmount": 4,
		"dropChance": 0.5,
		"replaceable": false,
		"isAnchor": true
	},
	"stone": {
		"health": 1000,
		"collision": true,
		"diggable": true,
		"sprite": "stone.png",
		"replaceable": false,
		"isAnchor": true
	},
	"grass": {
		"health": 1000,
		"collision": true,
		"diggable": true,
		"sprite": "grass.png",
		"replaceable": false,
		"drops": "dirt",
		"dropAmount": 1,
		"dropChance": 1,
		"isAnchor": true
	},
	"void": {
		"health": 100000,
		"collision": false,
		"diggable": false,
		"sprite": "void.png",
		"replaceable": true,
		"isAnchor": true
	},
	"coal": {
		"health": 1000,
		"collision": true,
		"diggable": true,
		"sprite": "coal.png",
		"replaceable": false,
		"drops": "coal",
		"dropAmount": 3,
		"dropChance": 0.5,
		"isAnchor": true
	},
	"gold": {
		"health": 1000,
		"collision": true,
		"diggable": true,
		"sprite": "gold.png",
		"replaceable": false,
		"drops": "coal",
		"dropAmount": 3,
		"dropChance": 0.5,
		"isAnchor": true
	},
	"ladder": {
		"health": 1000,
		"collision": false,
		"disableGravity": true,
		"diggable": true,
		"sprite": "ladder.png",
		"replaceable": false,
		"drops": "ladder",
		"dropAmount": 1,
		"dropChance": 1,
		"isAnchor": true
	},
	"leaves": {
		"health": 1000,
		"collision": false,
		"diggable": true,
		"sprite": "leaves.png",
		"replaceable": true,
		"isAnchor": false
	},
	"silver": {
		"health": 1000,
		"collision": true,
		"diggable": true,
		"sprite": "silver.png",
		"replaceable": false,
		"drops": "silver",
		"dropAmount": 1,
		"dropChance": 1,
		"isAnchor": true
	},
	"sulfur": {
		"health": 1000,
		"collision": true,
		"diggable": true,
		"sprite": "sulfur.png",
		"replaceable": false,
		"drops": "sulfur",
		"dropAmount": 1,
		"dropChance": 1,
		"isAnchor": true
	},
	"uran": {
		"health": 1000,
		"collision": true,
		"diggable": true,
		"sprite": "uran.png",
		"replaceable": false,
		"drops": "uran",
		"dropAmount": 1,
		"dropChance": 1,
		"isAnchor": true
	},
	"titan": {
		"health": 1000,
		"collision": true,
		"diggable": false,
		"sprite": "titan.png",
		"replaceable": false,
		"isAnchor": true
	},
	"wood": {
		"health": 1000,
		"collision": false,
		"diggable": true,
		"sprite": "wood.png",
		"replaceable": false,
		"drops": "wood",
		"dropAmount": 1,
		"dropChance": 1,
		"isAnchor": true
	}
}
